gullplot/__about__.py
gullplot/__init__.py
gullplot/__main__.py
gullplot/cli/__init__.py
gullplot-0.0.1.dist-info/METADATA
gullplot-0.0.1.dist-info/WHEEL
gullplot-0.0.1.dist-info/entry_points.txt
gullplot-0.0.1.dist-info/licenses/LICENSE.txt
gullplot-0.0.1.dist-info/RECORD
