Metadata-Version: 2.1
Name: gullplot
Version: 0.0.1
Summary: Terminal based plotting with seaborn
Author-email: Henry Watkins <h.watkins@ucl.ac.uk>
License-Expression: MIT
License-File: LICENSE.txt
Classifier: Programming Language :: Python
Requires-Python: >=3.9
Requires-Dist: click
Requires-Dist: matplotlib
Requires-Dist: pandas
Requires-Dist: seaborn
